typeduck/__init__.py
typeduck/_type_duck.py
typeduck-0.1.0.dist-info/METADATA
typeduck-0.1.0.dist-info/WHEEL
typeduck-0.1.0.dist-info/top_level.txt
typeduck-0.1.0.dist-info/zip-safe
typeduck-0.1.0.dist-info/RECORD
