Metadata-Version: 2.1
Name: typeduck
Version: 0.1.0
Summary: UNKNOWN
Home-page: https://github.com/den4uk/typeduck
Author: Denis Sazonov
Author-email: den@saz.lt
License: MIT License
Keywords: typing,annotations,match,check,compare,validate,validation
Platform: UNKNOWN
Classifier: Programming Language :: Python :: 3
Classifier: License :: OSI Approved :: MIT License
Classifier: Operating System :: OS Independent
Requires-Python: >=3.8
